container_cli/__init__.py
container_cli/__main__.py
container_cli/change_ports.py
container_cli/update.py
container_cli-1.0.1.dist-info/LICENSE
container_cli-1.0.1.dist-info/METADATA
container_cli-1.0.1.dist-info/WHEEL
container_cli-1.0.1.dist-info/entry_points.txt
container_cli-1.0.1.dist-info/top_level.txt
container_cli-1.0.1.dist-info/RECORD
