Metadata-Version: 2.1
Name: container-cli
Version: 1.0.1
Summary: ✨A non-antihuman way to modify docker's container port mapping✨
Home-page: https://github.com/yixinNB/container-cli
Author: yixinNB_github
Project-URL: Documentation, https://github.com/yixinNB/container-cli
Project-URL: Code, https://github.com/yixinNB/container-cli
Project-URL: Issue tracker, https://github.com/yixinNB/container-cli/issues
License-File: LICENSE
Requires-Dist: loguru (>=0.7)
Requires-Dist: checkopt (>=1)
Requires-Dist: questionary (>=2)
